yarqueue/__init__.py
yarqueue/base_queue.py
yarqueue/compat.py
yarqueue/constants.py
yarqueue/queue.py
yarqueue/serializer.py
yarqueue-0.4.1.dist-info/LICENSE
yarqueue-0.4.1.dist-info/METADATA
yarqueue-0.4.1.dist-info/WHEEL
yarqueue-0.4.1.dist-info/entry_points.txt
yarqueue-0.4.1.dist-info/top_level.txt
yarqueue-0.4.1.dist-info/RECORD
