Metadata-Version: 2.1
Name: yarqueue
Version: 0.4.1
Summary: Yet Another python queue backed by redis; but modern and compliant
Home-page: https://github.com/clbarnes/yarqueue
Author: Chris L. Barnes
Author-email: barnesc@janelia.hhmi.org
License: MIT license
Keywords: yarqueue queue multiprocessing hotqueue redis redislite
Platform: UNKNOWN
Classifier: Development Status :: 2 - Pre-Alpha
Classifier: Intended Audience :: Developers
Classifier: License :: OSI Approved :: MIT License
Classifier: Natural Language :: English
Classifier: Programming Language :: Python :: 3
Classifier: Programming Language :: Python :: 3.6
Classifier: Programming Language :: Python :: 3.7
Requires-Dist: redis (>=3.2)
Requires-Dist: StrEnum (>=0.4)
Provides-Extra: all
Requires-Dist: redislite (>=5.0) ; extra == 'all'
Requires-Dist: flask ; extra == 'all'
Requires-Dist: tqdm ; extra == 'all'
Requires-Dist: click ; extra == 'all'
Requires-Dist: pickle5 ; (python_version >= "3.6" and python_version < "3.8") and extra == 'all'
Provides-Extra: cli
Requires-Dist: click ; extra == 'cli'
Requires-Dist: tqdm ; extra == 'cli'
Provides-Extra: http
Requires-Dist: click ; extra == 'http'
Requires-Dist: flask ; extra == 'http'
Provides-Extra: pickle
Requires-Dist: pickle5 ; (python_version >= "3.6" and python_version < "3.8") and extra == 'pickle'
Provides-Extra: redislite
Requires-Dist: redislite (>=5.0) ; extra == 'redislite'
